glimmr/__init__.py
glimmr/exceptions.py
glimmr/glimmr.py
glimmr/models.py
src/glimmr/__init__.py
src/glimmr/exceptions.py
src/glimmr/glimmr.py
src/glimmr/models.py
tests/__init__.py
tests/test_glimmr.py
tests/test_wled.py
glimmr-1.2.0.dist-info/LICENSE
glimmr-1.2.0.dist-info/LICENSE.md
glimmr-1.2.0.dist-info/METADATA
glimmr-1.2.0.dist-info/WHEEL
glimmr-1.2.0.dist-info/top_level.txt
glimmr-1.2.0.dist-info/RECORD
